web_aaron_alphabet/__init__.py
web_aaron_alphabet/__main__.py
web_aaron_alphabet/harvesting.py
web_aaron_alphabet/converting/__init__.py
web_aaron_alphabet/converting/htmldocx.py
web_aaron_alphabet/converting/pdfkit.py
web_aaron_alphabet/converting/weasyprint.py
web_aaron_alphabet/converting/wkhtmltopdf.py
web_aaron_alphabet/merging/PyPDF2.py
web_aaron_alphabet/merging/__init__.py
web_aaron_alphabet/merging/pypdf.py
web_aaron_alphabet-0.0.7.dist-info/LICENSE
web_aaron_alphabet-0.0.7.dist-info/METADATA
web_aaron_alphabet-0.0.7.dist-info/WHEEL
web_aaron_alphabet-0.0.7.dist-info/top_level.txt
web_aaron_alphabet-0.0.7.dist-info/RECORD
