Metadata-Version: 2.1
Name: web-aaron-alphabet
Version: 0.0.7
Summary: Websites to PDFs. 
Author-email: Aaron Alphabet <aaron.alphabet@posteo.org>
License: Copyright © 2023 Aaron Alphabet
Classifier: License :: OSI Approved :: MIT License
Classifier: Programming Language :: Python
Classifier: Programming Language :: Python :: 3
Requires-Python: >=3.11
License-File: LICENSE
Requires-Dist: PyPDF2
Requires-Dist: pdfkit
Requires-Dist: pypdf
Requires-Dist: wkhtmltopdf
Requires-Dist: docx2pdf
Requires-Dist: htmldocx
Requires-Dist: weasyprint
